{
  "updatedAt": "2026-07-19T21:07:22.250Z",
  "music": [
    {
      "track": "Dialectos da Ternura",
      "artist": "Da Weasel",
      "album": "Amor, Escárnio E Maldizer",
      "url": "https://www.last.fm/music/Da%20Weasel/_/Dialectos%20da%20Ternura",
      "image": "https://lastfm.freetls.fastly.net/i/u/300x300/a4c82fa706e5e4c103b6478bbdc25213.jpg",
      "playedAt": "2026-07-19T10:42:23.000Z",
      "nowPlaying": false
    },
    {
      "track": "Põe a Mão No Ar",
      "artist": "Mundo Secreto",
      "album": "EP Digital",
      "url": "https://www.last.fm/music/Mundo%20Secreto/_/P%C3%B5e%20a%20M%C3%A3o%20No%20Ar",
      "image": "https://lastfm.freetls.fastly.net/i/u/300x300/f06c2568dbbcef698a6f234b7cf5484f.jpg",
      "playedAt": "2026-07-19T10:38:53.000Z",
      "nowPlaying": false
    },
    {
      "track": "Põe A Mão No Ar",
      "artist": "Francisco Ribeiro",
      "album": "EP Digital",
      "url": "https://www.last.fm/music/Francisco%20Ribeiro/_/P%C3%B5e%20A%20M%C3%A3o%20No%20Ar",
      "image": null,
      "playedAt": "2026-07-19T10:38:53.000Z",
      "nowPlaying": false
    },
    {
      "track": "Pára-me Agora",
      "artist": "Ornatos Violeta",
      "album": "Inéditos/Raridades",
      "url": "https://www.last.fm/music/Ornatos%20Violeta/_/P%C3%A1ra-me%20Agora",
      "image": "https://lastfm.freetls.fastly.net/i/u/300x300/3b13859441c04ad0af6007d55c335d1b.jpg",
      "playedAt": "2026-07-19T10:36:04.000Z",
      "nowPlaying": false
    },
    {
      "track": "Miúda do café",
      "artist": "Amor Electro",
      "album": "#4",
      "url": "https://www.last.fm/music/Amor%20Electro/_/Mi%C3%BAda%20do%20caf%C3%A9",
      "image": "https://lastfm.freetls.fastly.net/i/u/300x300/ab676b069f0ae86c3e18e62d282deb07.jpg",
      "playedAt": "2026-07-19T10:31:22.000Z",
      "nowPlaying": false
    }
  ],
  "books": [
    {
      "title": "Amêndoas",
      "author": "Sohn Won-Pyung",
      "url": "https://www.goodreads.com/book/show/211948994",
      "cover": "https://i.gr-assets.com/images/S/compressed.photo.goodreads.com/books/1713738383l/211948994._SX318_.jpg",
      "readAt": "2026-07-06T00:00:00.000Z"
    },
    {
      "title": "Lost Lambs",
      "author": "Madeline Cash",
      "url": "https://www.goodreads.com/book/show/246288258",
      "cover": "https://i.gr-assets.com/images/S/compressed.photo.goodreads.com/books/1767858948l/246288258._SY475_.jpg",
      "readAt": "2026-06-24T00:00:00.000Z"
    },
    {
      "title": "Contra o Progresso",
      "author": "Slavoj Žižek",
      "url": "https://www.goodreads.com/book/show/241412474",
      "cover": "https://i.gr-assets.com/images/S/compressed.photo.goodreads.com/books/1757427682l/241412474._SY475_.jpg",
      "readAt": "2026-06-13T00:00:00.000Z"
    },
    {
      "title": "A Leste do Paraíso",
      "author": "John Steinbeck",
      "url": "https://www.goodreads.com/book/show/40637252",
      "cover": "https://i.gr-assets.com/images/S/compressed.photo.goodreads.com/books/1727453838l/40637252._SY475_.jpg",
      "readAt": "2026-06-11T00:00:00.000Z"
    },
    {
      "title": "Klara and the Sun",
      "author": "Kazuo Ishiguro",
      "url": "https://www.goodreads.com/book/show/58256542",
      "cover": "https://i.gr-assets.com/images/S/compressed.photo.goodreads.com/books/1646458875l/58256542._SY475_.jpg",
      "readAt": "2026-05-10T00:00:00.000Z"
    }
  ],
  "films": [
    {
      "title": "The Devil Wears Prada 2",
      "year": "2026",
      "rating": 2,
      "rewatch": false,
      "url": "https://letterboxd.com/film/the-devil-wears-prada-2/",
      "poster": "https://a.ltrbxd.com/resized/film-poster/1/1/9/5/5/8/6/1195586-the-devil-wears-prada-2-0-600-0-900-crop.jpg?v=0d955add69",
      "watchedAt": "2026-05-09T00:00:00.000Z"
    }
  ],
  "series": [
    {
      "show": "Hacks",
      "year": 2021,
      "season": 4,
      "number": 2,
      "episode": "Cover Girls",
      "url": "https://trakt.tv/shows/hacks-2021",
      "tmdb": 124101,
      "image": "https://image.tmdb.org/t/p/w342/ca5XiEFgyGsI38QT3wEKa1QVGX.jpg",
      "watchedAt": "2026-07-19T16:41:00.000Z"
    },
    {
      "show": "The Bear",
      "year": 2022,
      "season": 5,
      "number": 8,
      "episode": "The Original Beef of Chicagoland",
      "url": "https://trakt.tv/shows/the-bear",
      "tmdb": 136315,
      "image": "https://image.tmdb.org/t/p/w342/eKfVzzEazSIjJMrw9ADa2x8ksLz.jpg",
      "watchedAt": "2026-07-18T20:45:00.000Z"
    },
    {
      "show": "The Americans",
      "year": 2013,
      "season": 5,
      "number": 9,
      "episode": "IHOP",
      "url": "https://trakt.tv/shows/the-americans-2013",
      "tmdb": 46533,
      "image": "https://image.tmdb.org/t/p/w342/w1UBlxEXhbKe8sp0fxFZh7MqTce.jpg",
      "watchedAt": "2026-07-18T19:42:00.000Z"
    }
  ]
}
