{
  "updatedAt": "2026-07-03T07:36:47.621Z",
  "listening": {
    "track": "Porcelana",
    "artist": "ROSALÍA",
    "album": "LUX",
    "url": "https://www.last.fm/music/ROSAL%C3%8DA/_/Porcelana",
    "image": "https://lastfm.freetls.fastly.net/i/u/300x300/0e6bf07983158660ec4e00cae318ba83.jpg",
    "playedAt": "2026-07-02T22:41:15.000Z",
    "nowPlaying": false
  },
  "reading": {
    "title": "Amêndoas",
    "author": "Sohn Won-Pyung",
    "url": "https://www.goodreads.com/book/show/211948994",
    "cover": "https://i.gr-assets.com/images/S/compressed.photo.goodreads.com/books/1713738383l/211948994._SX318_.jpg",
    "startedAt": "2026-06-28T09:44:20.000Z"
  },
  "watching": {
    "title": "The Devil Wears Prada 2",
    "year": "2026",
    "rating": 2,
    "rewatch": false,
    "url": "https://letterboxd.com/film/the-devil-wears-prada-2/",
    "poster": "https://a.ltrbxd.com/resized/film-poster/1/1/9/5/5/8/6/1195586-the-devil-wears-prada-2-0-600-0-900-crop.jpg?v=0d955add69",
    "watchedAt": "2026-05-09T00:00:00.000Z"
  }
}
